setup.py
kernel_api_client/__init__.py
kernel_api_client/api_client.py
kernel_api_client/configuration.py
kernel_api_client/rest.py
kernel_api_client.egg-info/PKG-INFO
kernel_api_client.egg-info/SOURCES.txt
kernel_api_client.egg-info/dependency_links.txt
kernel_api_client.egg-info/requires.txt
kernel_api_client.egg-info/top_level.txt
kernel_api_client/apis/__init__.py
kernel_api_client/apis/geographies_api.py
kernel_api_client/apis/metrics_api.py
kernel_api_client/apis/token_api.py
kernel_api_client/apis/user_api.py
kernel_api_client/models/__init__.py
kernel_api_client/models/auth_token.py
kernel_api_client/models/column_description.py
kernel_api_client/models/extended_user_profile.py
kernel_api_client/models/forecast_metadata.py
kernel_api_client/models/general_error.py
kernel_api_client/models/geography.py
kernel_api_client/models/geography_level.py
kernel_api_client/models/metric.py
kernel_api_client/models/subscribed_crop.py
kernel_api_client/models/table.py
kernel_api_client/models/table_row.py
kernel_api_client/models/user_profile.py
test/__init__.py
test/test_auth_token.py
test/test_column_description.py
test/test_extended_user_profile.py
test/test_forecast_metadata.py
test/test_general_error.py
test/test_geographies_api.py
test/test_geography.py
test/test_geography_level.py
test/test_metric.py
test/test_metrics_api.py
test/test_subscribed_crop.py
test/test_table.py
test/test_table_row.py
test/test_token_api.py
test/test_user_api.py
test/test_user_profile.py